[
  {
    "code": "101",
    "name": "阿富汗"
  },
  {
    "code": "102",
    "name": "巴林"
  },
  {
    "code": "103",
    "name": "孟加拉国"
  },
  {
    "code": "104",
    "name": "不丹"
  },
  {
    "code": "105",
    "name": "文莱"
  },
  {
    "code": "106",
    "name": "缅甸"
  },
  {
    "code": "107",
    "name": "柬埔寨"
  },
  {
    "code": "108",
    "name": "塞浦路斯"
  },
  {
    "code": "109",
    "name": "朝鲜"
  },
  {
    "code": "110",
    "name": "香港"
  },
  {
    "code": "111",
    "name": "印度"
  },
  {
    "code": "112",
    "name": "印度尼西亚"
  },
  {
    "code": "113",
    "name": "伊朗"
  },
  {
    "code": "114",
    "name": "伊拉克"
  },
  {
    "code": "115",
    "name": "以色列"
  },
  {
    "code": "116",
    "name": "日本"
  },
  {
    "code": "117",
    "name": "约旦"
  },
  {
    "code": "118",
    "name": "科威特"
  },
  {
    "code": "119",
    "name": "老挝"
  },
  {
    "code": "120",
    "name": "黎巴嫩"
  },
  {
    "code": "121",
    "name": "澳门"
  },
  {
    "code": "122",
    "name": "马来西亚"
  },
  {
    "code": "123",
    "name": "马尔代夫"
  },
  {
    "code": "124",
    "name": "蒙古"
  },
  {
    "code": "125",
    "name": "尼泊尔联邦民主共和国"
  },
  {
    "code": "126",
    "name": "阿曼"
  },
  {
    "code": "127",
    "name": "巴基斯坦"
  },
  {
    "code": "128",
    "name": "巴勒斯坦"
  },
  {
    "code": "129",
    "name": "菲律宾"
  },
  {
    "code": "130",
    "name": "卡塔尔"
  },
  {
    "code": "131",
    "name": "沙特阿拉伯"
  },
  {
    "code": "132",
    "name": "新加坡"
  },
  {
    "code": "133",
    "name": "韩国"
  },
  {
    "code": "134",
    "name": "斯里兰卡"
  },
  {
    "code": "135",
    "name": "叙利亚"
  },
  {
    "code": "136",
    "name": "泰国"
  },
  {
    "code": "137",
    "name": "土耳其"
  },
  {
    "code": "138",
    "name": "阿联酋"
  },
  {
    "code": "139",
    "name": "也门"
  },
  {
    "code": "141",
    "name": "越南"
  },
  {
    "code": "142",
    "name": "中国"
  },
  {
    "code": "144",
    "name": "东帝汶"
  },
  {
    "code": "145",
    "name": "哈萨克斯坦"
  },
  {
    "code": "146",
    "name": "吉尔吉斯斯坦"
  },
  {
    "code": "147",
    "name": "塔吉克斯坦"
  },
  {
    "code": "148",
    "name": "土库曼斯坦"
  },
  {
    "code": "149",
    "name": "乌兹别克斯坦"
  },
  {
    "code": "199",
    "name": "亚洲其他国家(地区)"
  },
  {
    "code": "201",
    "name": "阿尔及利亚"
  },
  {
    "code": "202",
    "name": "安哥拉"
  },
  {
    "code": "203",
    "name": "贝宁"
  },
  {
    "code": "204",
    "name": "博茨瓦那"
  },
  {
    "code": "205",
    "name": "布隆迪"
  },
  {
    "code": "206",
    "name": "喀麦隆"
  },
  {
    "code": "208",
    "name": "佛得角"
  },
  {
    "code": "209",
    "name": "中非"
  },
  {
    "code": "210",
    "name": "塞卜泰(休达)"
  },
  {
    "code": "211",
    "name": "乍得"
  },
  {
    "code": "212",
    "name": "科摩罗"
  },
  {
    "code": "213",
    "name": "刚果(布)"
  },
  {
    "code": "214",
    "name": "吉布提"
  },
  {
    "code": "215",
    "name": "埃及"
  },
  {
    "code": "216",
    "name": "赤道几内亚"
  },
  {
    "code": "217",
    "name": "埃塞俄比亚"
  },
  {
    "code": "218",
    "name": "加蓬"
  },
  {
    "code": "219",
    "name": "冈比亚"
  },
  {
    "code": "220",
    "name": "加纳"
  },
  {
    "code": "221",
    "name": "几内亚"
  },
  {
    "code": "222",
    "name": "几内亚比绍"
  },
  {
    "code": "223",
    "name": "科特迪瓦"
  },
  {
    "code": "224",
    "name": "肯尼亚"
  },
  {
    "code": "225",
    "name": "利比里亚"
  },
  {
    "code": "226",
    "name": "利比亚"
  },
  {
    "code": "227",
    "name": "马达加斯加"
  },
  {
    "code": "228",
    "name": "马拉维"
  },
  {
    "code": "229",
    "name": "马里"
  },
  {
    "code": "230",
    "name": "毛里塔尼亚"
  },
  {
    "code": "231",
    "name": "毛里求斯"
  },
  {
    "code": "232",
    "name": "摩洛哥"
  },
  {
    "code": "233",
    "name": "莫桑比克"
  },
  {
    "code": "234",
    "name": "纳米比亚"
  },
  {
    "code": "235",
    "name": "尼日尔"
  },
  {
    "code": "236",
    "name": "尼日利亚"
  },
  {
    "code": "237",
    "name": "留尼汪"
  },
  {
    "code": "238",
    "name": "卢旺达"
  },
  {
    "code": "239",
    "name": "圣多美和普林西比"
  },
  {
    "code": "240",
    "name": "塞内加尔"
  },
  {
    "code": "241",
    "name": "塞舌尔"
  },
  {
    "code": "242",
    "name": "塞拉利昂"
  },
  {
    "code": "243",
    "name": "索马里"
  },
  {
    "code": "244",
    "name": "南非"
  },
  {
    "code": "245",
    "name": "西撒哈拉"
  },
  {
    "code": "246",
    "name": "苏丹"
  },
  {
    "code": "247",
    "name": "坦桑尼亚"
  },
  {
    "code": "248",
    "name": "多哥"
  },
  {
    "code": "249",
    "name": "突尼斯"
  },
  {
    "code": "250",
    "name": "乌干达"
  },
  {
    "code": "251",
    "name": "布基纳法索"
  },
  {
    "code": "253",
    "name": "赞比亚"
  },
  {
    "code": "254",
    "name": "津巴布韦"
  },
  {
    "code": "255",
    "name": "莱索托"
  },
  {
    "code": "256",
    "name": "梅利利亚"
  },
  {
    "code": "257",
    "name": "斯威士兰"
  },
  {
    "code": "258",
    "name": "厄立特里亚"
  },
  {
    "code": "259",
    "name": "马约特"
  },
  {
    "code": "299",
    "name": "非洲其他国家(地区)"
  },
  {
    "code": "301",
    "name": "比利时"
  },
  {
    "code": "302",
    "name": "丹麦"
  },
  {
    "code": "303",
    "name": "英国"
  },
  {
    "code": "304",
    "name": "德国"
  },
  {
    "code": "305",
    "name": "法国"
  },
  {
    "code": "306",
    "name": "爱尔兰"
  },
  {
    "code": "307",
    "name": "意大利"
  },
  {
    "code": "308",
    "name": "卢森堡"
  },
  {
    "code": "309",
    "name": "荷兰"
  },
  {
    "code": "310",
    "name": "希腊"
  },
  {
    "code": "311",
    "name": "葡萄牙"
  },
  {
    "code": "312",
    "name": "西班牙"
  },
  {
    "code": "313",
    "name": "阿尔巴尼亚"
  },
  {
    "code": "314",
    "name": "安道尔"
  },
  {
    "code": "315",
    "name": "奥地利"
  },
  {
    "code": "316",
    "name": "保加利亚"
  },
  {
    "code": "318",
    "name": "芬兰"
  },
  {
    "code": "320",
    "name": "直布罗陀"
  },
  {
    "code": "321",
    "name": "匈牙利"
  },
  {
    "code": "322",
    "name": "冰岛"
  },
  {
    "code": "323",
    "name": "列支敦士登"
  },
  {
    "code": "324",
    "name": "马耳他"
  },
  {
    "code": "325",
    "name": "摩纳哥"
  },
  {
    "code": "326",
    "name": "挪威"
  },
  {
    "code": "327",
    "name": "波兰"
  },
  {
    "code": "328",
    "name": "罗马尼亚"
  },
  {
    "code": "329",
    "name": "圣马力诺"
  },
  {
    "code": "330",
    "name": "瑞典"
  },
  {
    "code": "331",
    "name": "瑞士"
  },
  {
    "code": "334",
    "name": "爱沙尼亚"
  },
  {
    "code": "335",
    "name": "拉脱维亚"
  },
  {
    "code": "336",
    "name": "立陶宛"
  },
  {
    "code": "337",
    "name": "格鲁吉亚"
  },
  {
    "code": "338",
    "name": "亚美尼亚"
  },
  {
    "code": "339",
    "name": "阿塞拜疆"
  },
  {
    "code": "340",
    "name": "白俄罗斯"
  },
  {
    "code": "343",
    "name": "摩尔多瓦"
  },
  {
    "code": "344",
    "name": "俄罗斯联邦"
  },
  {
    "code": "347",
    "name": "乌克兰"
  },
  {
    "code": "349",
    "name": "塞尔维亚和黑山"
  },
  {
    "code": "350",
    "name": "斯洛文尼亚"
  },
  {
    "code": "351",
    "name": "克罗地亚"
  },
  {
    "code": "352",
    "name": "捷克"
  },
  {
    "code": "353",
    "name": "斯洛伐克"
  },
  {
    "code": "354",
    "name": "前南马其顿"
  },
  {
    "code": "355",
    "name": "波黑"
  },
  {
    "code": "356",
    "name": "梵蒂冈城国"
  },
  {
    "code": "357",
    "name": "法罗群岛"
  },
  {
    "code": "358",
    "name": "塞尔维亚"
  },
  {
    "code": "359",
    "name": "黑山"
  },
  {
    "code": "399",
    "name": "欧洲其他国家(地区)"
  },
  {
    "code": "401",
    "name": "安提瓜和巴布达"
  },
  {
    "code": "402",
    "name": "阿根廷"
  },
  {
    "code": "403",
    "name": "阿鲁巴"
  },
  {
    "code": "404",
    "name": "巴哈马"
  },
  {
    "code": "405",
    "name": "巴巴多斯"
  },
  {
    "code": "406",
    "name": "伯利兹"
  },
  {
    "code": "408",
    "name": "多民族玻利维亚国"
  },
  {
    "code": "410",
    "name": "巴西"
  },
  {
    "code": "411",
    "name": "开曼群岛"
  },
  {
    "code": "412",
    "name": "智利"
  },
  {
    "code": "413",
    "name": "哥伦比亚"
  },
  {
    "code": "414",
    "name": "多米尼克"
  },
  {
    "code": "415",
    "name": "哥斯达黎加"
  },
  {
    "code": "416",
    "name": "古巴"
  },
  {
    "code": "418",
    "name": "多米尼加共和国"
  },
  {
    "code": "419",
    "name": "厄瓜多尔"
  },
  {
    "code": "420",
    "name": "法属圭亚那"
  },
  {
    "code": "421",
    "name": "格林纳达"
  },
  {
    "code": "422",
    "name": "瓜德罗普"
  },
  {
    "code": "423",
    "name": "危地马拉"
  },
  {
    "code": "424",
    "name": "圭亚那"
  },
  {
    "code": "425",
    "name": "海地"
  },
  {
    "code": "426",
    "name": "洪都拉斯"
  },
  {
    "code": "427",
    "name": "牙买加"
  },
  {
    "code": "428",
    "name": "马提尼克"
  },
  {
    "code": "429",
    "name": "墨西哥"
  },
  {
    "code": "430",
    "name": "蒙特塞拉特"
  },
  {
    "code": "431",
    "name": "尼加拉瓜"
  },
  {
    "code": "432",
    "name": "巴拿马"
  },
  {
    "code": "433",
    "name": "巴拉圭"
  },
  {
    "code": "434",
    "name": "秘鲁"
  },
  {
    "code": "435",
    "name": "波多黎各"
  },
  {
    "code": "437",
    "name": "圣卢西亚"
  },
  {
    "code": "438",
    "name": "圣马丁岛"
  },
  {
    "code": "439",
    "name": "圣文森特和格林纳丁斯"
  },
  {
    "code": "440",
    "name": "萨尔瓦多"
  },
  {
    "code": "441",
    "name": "苏里南"
  },
  {
    "code": "442",
    "name": "特立尼达和多巴哥"
  },
  {
    "code": "443",
    "name": "特克斯和凯科斯群岛"
  },
  {
    "code": "444",
    "name": "乌拉圭"
  },
  {
    "code": "445",
    "name": "委内瑞拉"
  },
  {
    "code": "446",
    "name": "英属维尔京群岛"
  },
  {
    "code": "448",
    "name": "圣皮埃尔和密克隆"
  },
  {
    "code": "449",
    "name": "荷属安地列斯"
  },
  {
    "code": "501",
    "name": "加拿大"
  },
  {
    "code": "502",
    "name": "美国"
  },
  {
    "code": "503",
    "name": "格陵兰"
  },
  {
    "code": "504",
    "name": "百慕大"
  },
  {
    "code": "601",
    "name": "澳大利亚"
  },
  {
    "code": "602",
    "name": "库克群岛"
  },
  {
    "code": "603",
    "name": "斐济"
  },
  {
    "code": "606",
    "name": "瑙鲁"
  },
  {
    "code": "607",
    "name": "新喀里多尼亚"
  },
  {
    "code": "608",
    "name": "瓦努阿图"
  },
  {
    "code": "609",
    "name": "新西兰"
  },
  {
    "code": "610",
    "name": "诺福克岛"
  },
  {
    "code": "611",
    "name": "巴布亚新几内亚"
  },
  {
    "code": "613",
    "name": "所罗门群岛"
  },
  {
    "code": "614",
    "name": "汤加"
  },
  {
    "code": "617",
    "name": "萨摩亚"
  },
  {
    "code": "618",
    "name": "基里巴斯"
  },
  {
    "code": "619",
    "name": "图瓦卢"
  },
  {
    "code": "621",
    "name": "马绍尔群岛"
  },
  {
    "code": "622",
    "name": "帕劳"
  },
  {
    "code": "623",
    "name": "法属波利尼西亚"
  },
  {
    "code": "625",
    "name": "瓦利斯和浮图纳"
  },
  {
    "code": "143",
    "name": "中国台湾"
  }
]